gnvext/__init__.py
gnvext/converters/base.py
gnvext/converters/converters.py
gnvext-2.0.1.dist-info/LICENSE
gnvext-2.0.1.dist-info/METADATA
gnvext-2.0.1.dist-info/WHEEL
gnvext-2.0.1.dist-info/top_level.txt
gnvext-2.0.1.dist-info/RECORD
