Metadata-Version: 2.2
Name: gnvext
Version: 2.0.1
Summary: Wrapper for converting environment variables to any python type
Author: DouleLove
License: The MIT License (MIT)
Project-URL: Homepage, https://github.com/DouleLove/getenv_ext
Project-URL: Issues, https://github.com/DouleLove/getenv_ext/issues
Project-URL: Repository, https://github.com/DouleLove/getenv_ext
Classifier: Development Status :: 3 - Alpha
Classifier: Intended Audience :: Developers
Classifier: Topic :: Utilities
Classifier: Natural Language :: English
Classifier: Operating System :: OS Independent
Classifier: License :: OSI Approved :: MIT License
Classifier: Programming Language :: Python :: 3.10
Classifier: Programming Language :: Python :: 3.11
Classifier: Programming Language :: Python :: 3.12
Requires-Python: >=3.10
License-File: LICENSE
Provides-Extra: lint
Requires-Dist: black==24.10.0; extra == "lint"
Requires-Dist: flake8==7.1.1; extra == "lint"
Requires-Dist: flake8-isort==6.1.1; extra == "lint"
Requires-Dist: Flake8-pyproject==1.2.3; extra == "lint"
